Quran_Module/Quran_Arabic.csv
Quran_Module/Quran_English.csv
Quran_Module/Quran_Module.py
Quran_Module/__init__.py
TheQuranModule-0.1.dist-info/LICENSE
TheQuranModule-0.1.dist-info/METADATA
TheQuranModule-0.1.dist-info/WHEEL
TheQuranModule-0.1.dist-info/top_level.txt
TheQuranModule-0.1.dist-info/RECORD
