Metadata-Version: 2.1
Name: TheQuranModule
Version: 0.1
Summary: Access Quran in Python with as little as three lines of code. With Both English and Arabic Support.
Home-page: https://github.com/UBISOFT-1/Quran_Module
Author: Muneeb A.
Author-email: muneeb@muneeb.co
License: MIT
Classifier: License :: OSI Approved :: MIT License
Classifier: Programming Language :: Python
Classifier: Programming Language :: Python :: 3
Classifier: Programming Language :: Python :: Implementation :: CPython
Classifier: Programming Language :: Python :: Implementation :: PyPy
Requires-Python: >=3.6
License-File: LICENSE
